fipipkg/__init__.py
fipipkg/verify.py
fipipkg-0.1.dev2.dist-info/DESCRIPTION.rst
fipipkg-0.1.dev2.dist-info/METADATA
fipipkg-0.1.dev2.dist-info/RECORD
fipipkg-0.1.dev2.dist-info/WHEEL
fipipkg-0.1.dev2.dist-info/entry_points.txt
fipipkg-0.1.dev2.dist-info/metadata.json
fipipkg-0.1.dev2.dist-info/top_level.txt
